pymedphys_analysis/__init__.py
pymedphys_analysis/_install_requires.py
pymedphys_analysis/_version.py
pymedphys_analysis/geometry/__init__.py
pymedphys_analysis/geometry/cube.py
pymedphys_analysis/mocks/__init__.py
pymedphys_analysis/mocks/profiles.py
pymedphys_analysis/winstonlutz/__init__.py
pymedphys_analysis/winstonlutz/profiles.py
pymedphys_analysis-0.11.0.dist-info/LICENSE-AGPL-3.0-or-later
pymedphys_analysis-0.11.0.dist-info/LICENSE-Apache-2.0
pymedphys_analysis-0.11.0.dist-info/METADATA
pymedphys_analysis-0.11.0.dist-info/WHEEL
pymedphys_analysis-0.11.0.dist-info/top_level.txt
pymedphys_analysis-0.11.0.dist-info/RECORD
